{
	"dsfdsf2333": {
		"userId": "dsfdsf2333",
		"password": "dsfdsf2333",
		"nickname": "大是大"
	},
	"dsfdsf2333fdfdf": {
		"userId": "dsfdsf2333fdfdf",
		"password": "dsfdsf2333",
		"nickname": "大是大"
	},
	"fdfsdfsdfsdf34": {
		"userId": "fdfsdfsdfsdf34",
		"password": "fsdfsdf34",
		"nickname": "防守打法"
	},
	"fdfsdfsdfsdf34ds": {
		"userId": "fdfsdfsdfsdf34ds",
		"password": "fsdfsdf34",
		"nickname": "防守打法"
	},
	"sfsdfsdfsdfsdf43244": {
		"userId": "sfsdfsdfsdfsdf43244",
		"password": "fkdsdfjlkjlsk433244",
		"nickname": "是是否"
	},
	"dsfsdfsdf342": {
		"userId": "dsfsdfsdf342",
		"password": "sdfsdf2334232",
		"nickname": "第三方"
	},
	"yyj744132102": {
		"userId": "yyj744132102",
		"password": "yyj744132102",
		"nickname": "袁远俊",
		"rooms": [
			"fdgfdg",
			"测试房间",
			"dsfsdfd",
			"wwewe",
			"gfdgdfgdf",
			"fdsfsdf",
			"fsdfsdfsd"
		]
	},
	"yyj742fsdsdfsdsdf": {
		"userId": "yyj742fsdsdfsdsdf",
		"password": "yyj742fsdsdfsdsdf",
		"nickname": "地方"
	}
}